pyropatch/__init__.py
pyropatch/pyropatch.py
pyropatch/version.py
pyropatch/command_handler/__init__.py
pyropatch/command_handler/command_handler.py
pyropatch/flood_handler/__init__.py
pyropatch/flood_handler/flood_handler.py
pyropatch/listen/__init__.py
pyropatch/listen/callback.py
pyropatch/listen/inline_query.py
pyropatch/listen/inline_result.py
pyropatch/listen/message.py
pyropatch/utils/__init__.py
pyropatch/utils/utils.py
pyropatch-2.1.dist-info/LICENSE
pyropatch-2.1.dist-info/METADATA
pyropatch-2.1.dist-info/WHEEL
pyropatch-2.1.dist-info/top_level.txt
pyropatch-2.1.dist-info/RECORD
