Metadata-Version: 2.1
Name: pyropatch
Version: 2.1
Summary: An advanced monkeypatcher add-on for Pyrogram
Home-page: https://github.com/rahulps1000/pyropatch
Author: Rahul P S
Author-email: rahulps1000@gmail.com
License: LGPLv3+
Classifier: Programming Language :: Python :: 3
Classifier: License :: OSI Approved :: GNU Lesser General Public License v3 or later (LGPLv3+)
Classifier: Operating System :: OS Independent
Requires-Python: ~=3.7
License-File: LICENSE
Requires-Dist: Pyrogram (>=2.0.16)
Requires-Dist: asyncio (~=3.4.3)
